just_d4rl/__init__.py
just_d4rl/d4rl_infos.py
just_d4rl/offline_env.py
just_d4rl-0.2407.5.dist-info/METADATA
just_d4rl-0.2407.5.dist-info/WHEEL
just_d4rl-0.2407.5.dist-info/top_level.txt
just_d4rl-0.2407.5.dist-info/RECORD
